README.md
setup.cfg
setup.py
sqlalchemy_explore/__init__.py
sqlalchemy_explore/__main__.py
sqlalchemy_explore/dump.py
sqlalchemy_explore/reflective.py
sqlalchemy_explore.egg-info/PKG-INFO
sqlalchemy_explore.egg-info/SOURCES.txt
sqlalchemy_explore.egg-info/dependency_links.txt
sqlalchemy_explore.egg-info/requires.txt
sqlalchemy_explore.egg-info/top_level.txt