Metadata-Version: 2.1
Name: sqlalchemy-explore
Version: 0.1.2
Summary: Utilities for working with pre-existing databases using SQLAlchemy
Home-page: https://github.com/aviadr1/sqlalchemy-explore
Author: Aviad Rozenhek
Author-email: aviadr1@gmail.com
License: MIT
Download-URL: https://github.com/aviadr1/sqlalchemy-explore/archive/v0.1.tar.gz
Keywords: SQLAlchemy,reflect,explore,dump,automap
Platform: UNKNOWN
Classifier: Development Status :: 3 - Alpha
Classifier: Intended Audience :: Developers
Classifier: Topic :: Software Development :: Build Tools
Classifier: License :: OSI Approved :: MIT License
Classifier: Programming Language :: Python :: 3
Classifier: Programming Language :: Python :: 3.7
